setup.py
ksurashanti_test_27/__init__.py
ksurashanti_test_27/first.py
ksurashanti_test_27/second.py
ksurashanti_test_27.egg-info/PKG-INFO
ksurashanti_test_27.egg-info/SOURCES.txt
ksurashanti_test_27.egg-info/dependency_links.txt
ksurashanti_test_27.egg-info/top_level.txt