Metadata-Version: 2.1
Name: ksurashanti-test-27
Version: 0.0.1
Summary: My Package
Author: Your Name
Author-email: ksurashanti@gmail.com
